README.md
setup.py
hellolan/__init__.py
hellolan/__main__.py
hellolan/hellolan.py
hellolan/ssh.py
hellolan.egg-info/PKG-INFO
hellolan.egg-info/SOURCES.txt
hellolan.egg-info/dependency_links.txt
hellolan.egg-info/entry_points.txt
hellolan.egg-info/requires.txt
hellolan.egg-info/top_level.txt