Metadata-Version: 2.1
Name: hellolan
Version: 0.0.8
Summary: Scan and filter devices on your local network.
Home-page: https://github.com/beasteers/hellolan
Author: Bea Steers
Author-email: bea.steers@gmail.com
License: MIT License
Keywords: port scanning filter hostname ip lan wan localhost 192.168 192.168.1.0 192.168.1.1
Platform: UNKNOWN
